pymata-express/__init__.py
pymata-express/digital_input_core.py
pymata-express/pin_data.py
pymata-express/private_constants.py
pymata-express/pymata4.py
pymata-express/pymata_express.py
pymata-express/pymata_express_serial.py
pymata_express/__init__.py
pymata_express/pin_data.py
pymata_express/private_constants.py
pymata_express/pymata_express.py
pymata_express/pymata_express_serial.py
pymata_express/pymata_express_socket.py
pymata_express-1.21.dist-info/METADATA
pymata_express-1.21.dist-info/WHEEL
pymata_express-1.21.dist-info/top_level.txt
pymata_express-1.21.dist-info/RECORD
